{"customerName":"Chris","customerEmail":"ikanga93@gmail.com","restaurantId":"niros_gyros","restaurantName":"Niro's Gyros","items":[{"id":"niros_gyros_italian_combo_sandwich_1","name":"Italian Combo Sandwich","price":8.99,"quantity":1,"options":[]}],"subtotal":8.99,"tax":0.7416750000000001,"total":10.292385000000001,"orderNumber":"RITT-20250506-62487","addToCart":true,"id":"TEMP-1746590251169-6900","createdAt":1746590251169,"expiresAt":1746763051169,"metadata":{"emailStatus":{"paymentLinkEmailSent":true,"paymentLinkEmailSentAt":1746590252483,"paymentLinkEmailMessageId":"Jztx-XSVRluewnxjAVq7Yg","paymentLinkEmailAttempts":1}}}